crimson/executable_types_beta/__init__.py
crimson/executable_types_beta/data_model.py
crimson/executable_types_beta/executor.py
crimson/executable_types_beta/mock.py
crimson/executable_types_beta/test.py
crimson/executable_types_beta/types.py
crimson/executable_types_beta/utils.py
crimson_executable_types_beta-0.1.1.dist-info/METADATA
crimson_executable_types_beta-0.1.1.dist-info/WHEEL
crimson_executable_types_beta-0.1.1.dist-info/top_level.txt
crimson_executable_types_beta-0.1.1.dist-info/RECORD
