Metadata-Version: 2.1
Name: crimson-executable-types-beta
Version: 0.1.1
Summary: Your package description.
Author-email: Sisung Kim <sisung.kim1@gmail.com>
Project-URL: Homepage, https://github.com/crimson206/executable-types
Project-URL: Bug Tracker, https://github.com/crimson206/executable-types/issues
Classifier: Development Status :: 2 - Pre-Alpha
Classifier: Programming Language :: Python :: 3
Classifier: Programming Language :: Python :: 3.9
Classifier: Programming Language :: Python :: 3.10
Classifier: Programming Language :: Python :: 3.11
Classifier: Programming Language :: Python :: 3.12
Classifier: Intended Audience :: Developers
Classifier: Topic :: Software Development :: Libraries :: Python Modules
Classifier: License :: OSI Approved :: MIT License
Classifier: Operating System :: OS Independent
Classifier: Typing :: Typed
Requires-Python: >=3.9
Requires-Dist: pydantic
Requires-Dist: crimson-auto-pydantic
Requires-Dist: crimson-ast-dev-tool
Requires-Dist: crimson-types-beta
